opf_tools/crop/__main__.py
opf_tools/crop/cropper.py
opf_tools/opf2colmap/__main__.py
opf_tools/opf2colmap/converter.py
opf_tools/opf2las/__main__.py
opf_tools/opf2las/converter.py
opf_tools/opf2nerf/__main__.py
opf_tools/opf2nerf/converter.py
opf_tools/opf2ply/__main__.py
opf_tools/opf2ply/converter.py
opf_tools/undistort/__main__.py
opf_tools/undistort/undistorter.py
pyopf/cameras/__init__.py
pyopf/cameras/calibrated_cameras.py
pyopf/cameras/camera_list.py
pyopf/cameras/gps_bias.py
pyopf/cameras/input_cameras.py
pyopf/cameras/input_rig_relatives.py
pyopf/cameras/projected_input_cameras.py
pyopf/cameras/sensor_internals.py
pyopf/cps/__init__.py
pyopf/cps/calibrated_control_points.py
pyopf/cps/constraints.py
pyopf/cps/input_control_points.py
pyopf/cps/projected_control_points.py
pyopf/crs/__init__.py
pyopf/crs/crs.py
pyopf/crs/geolocation.py
pyopf/crs/scene_reference_frame.py
pyopf/ext/__init__.py
pyopf/ext/pix4d_calibrated_intersection_tie_points.py
pyopf/ext/pix4d_input_depth_map.py
pyopf/ext/pix4d_input_intersection_tie_points.py
pyopf/ext/pix4d_planes.py
pyopf/ext/pix4d_polygonal_mesh.py
pyopf/ext/pix4d_region_of_interest.py
pyopf/ext/plane.py
pyopf/formats.py
pyopf/io/__init__.py
pyopf/io/loaders.py
pyopf/io/savers.py
pyopf/items.py
pyopf/pointcloud/__init__.py
pyopf/pointcloud/merge.py
pyopf/pointcloud/pcl.py
pyopf/pointcloud/utils.py
pyopf/project/__init__.py
pyopf/project/metadata.py
pyopf/project/project.py
pyopf/project/project_objects.py
pyopf/project/types.py
pyopf/resolve/__init__.py
pyopf/resolve/resolver.py
pyopf/types.py
pyopf/uid64.py
pyopf/util.py
pyopf/VersionInfo.py
pyopf/versions.py
pyopf-1.4.0.dist-info/entry_points.txt
pyopf-1.4.0.dist-info/LICENSE
pyopf-1.4.0.dist-info/METADATA
pyopf-1.4.0.dist-info/WHEEL
pyopf-1.4.0.dist-info/RECORD
