Metadata-Version: 2.1
Name: pyopf
Version: 1.4.0
Summary: Python library for I/O and manipulation of projects under the Open Photogrammetry Format (OPF)
Home-page: https://pix4d.github.io/opf-spec/specification/project.html
License: Apache-2.0
Keywords: photogrammetry,OPF
Author: Pix4D
Requires-Python: >=3.10
Classifier: Development Status :: 5 - Production/Stable
Classifier: License :: OSI Approved :: Apache Software License
Classifier: Operating System :: OS Independent
Classifier: Programming Language :: Python
Classifier: Programming Language :: Python :: 3
Classifier: Programming Language :: Python :: 3.10
Classifier: Programming Language :: Python :: 3.11
Classifier: Programming Language :: Python :: 3.12
Provides-Extra: tools
Requires-Dist: laspy (==2.4.1) ; extra == "tools"
Requires-Dist: numpy
Requires-Dist: pillow (>=10,<11)
Requires-Dist: plyfile (==0.9) ; extra == "tools"
Requires-Dist: pygltflib
Requires-Dist: pyproj (==3.6.0) ; extra == "tools"
Requires-Dist: python-dateutil
Requires-Dist: shapely ; extra == "tools"
Requires-Dist: simplejson
Requires-Dist: tqdm (>=4.65.0,<5.0.0) ; extra == "tools"
